{
    "resourceType":"Practitioner",
    "fieldsMapping":[
        
        {
            "iHRISForm":"region",
            "useForLinked":false,
            "iHRISField":[
                {
                    "fieldId":"id",
                    "iHRISFieldAlias":"id",
                    "fhirField":"value",
                    "active":false,
                    "fhirBaseElement":"identifier"
                }
            ],
            "extension":[],
            "iHRISJoinedForms":[
                {
                    "iHRISForm":"district",
                    "iHRISFormAlias":"district",
                    "iHRISFormJoinFieldSource":"id",
                    "iHRISFormJoinFieldDestination":"region",
                    "joiningConstraint":true,
                    "iHRISField":[
                    ],
                    "extension":[],
                    "iHRISJoinedForms":[
                        {
                            "iHRISForm":"county",
                            "iHRISFormAlias":"county",
                            "iHRISFormJoinFieldSource":"id",
                            "iHRISFormJoinFieldDestination":"district",
                            "joiningConstraint":true,
                            "iHRISField":[
                            ],
                            "extension":[],
                            "iHRISJoinedForms":[
                                {
                                    "iHRISForm":"health_area",
                                    "iHRISFormAlias":"health_area",
                                    "iHRISFormJoinFieldSource":"id",
                                    "iHRISFormJoinFieldDestination":"county",
                                    "joiningConstraint":true,
                                    "iHRISField":[
                                    ],
                                    "extension":[],
                                    "iHRISJoinedForms":[
                                        {
                                            "iHRISForm":"facility",
                                            "iHRISFormAlias":"facility",
                                            "iHRISFormJoinFieldSource":"id",
                                            "iHRISFormJoinFieldDestination":"location",
                                            "joiningConstraint":true,
                                            "iHRISField":[
                                            ],
                                            "extension":[],
                                            "iHRISJoinedForms":[
                                                {
                                                    "iHRISForm":"employment_status_rdc",
                                                    "iHRISFormAlias":"employment_status_rdc",
                                                    "iHRISFormJoinFieldSource":"id",
                                                    "iHRISFormJoinFieldDestination":"facility",
                                                    "joiningConstraint":true,
                                                    "iHRISField":[
                                                    ],
                                                    "extension":[],
                                                    "iHRISJoinedForms":[
                                                        {
                                                            "iHRISForm":"person",
                                                            "iHRISFormAlias":"person",
                                                            "iHRISFormJoinFieldSource":"parent",
                                                            "iHRISFormJoinFieldDestination":"id",
                                                            "joiningConstraint":true,
                                                            "iHRISField":[
                                                                {
                                                                    "fieldId":"csd_uuid",
                                                                    "iHRISFieldAlias":"uuid",
                                                                    "fhirField":"id",
                                                                    "active":true,
                                                                    "fhirBaseElement":"Practitioner"
                                                                },
                                                                {
                                                                    "fieldId":"id",
                                                                    "iHRISFieldAlias":"id",
                                                                    "fhirField":"value",
                                                                    "active":true,
                                                                    "fhirBaseElement":""
                                                                },
                                                                {
                                                                    "fieldId":"surname",
                                                                    "iHRISFieldAlias":"family",
                                                                    "fhirField":"family",
                                                                    "active":true,
                                                                    "fhirBaseElement":"name"
                                                                },
                                                                {
                                                                    "fieldId":"firstname",
                                                                    "iHRISFieldAlias":"given1",
                                                                    "fhirField":"given",
                                                                    "active":true,
                                                                    "fhirBaseElement":"name"
                                                                },
                                                                {
                                                                    "fieldId":"othername",
                                                                    "iHRISFieldAlias":"given2",
                                                                    "fhirField":"given",
                                                                    "active":false,
                                                                    "fhirBaseElement":"name"
                                                                } 
                                                            ],
                                                            "extension":[],
                                                            "iHRISJoinedForms":[
                                                                {
                                                                    "iHRISForm":"demographic",
                                                                    "iHRISFormAlias":"demographic",
                                                                    "iHRISFormJoinFieldSource":"id",
                                                                    "iHRISFormJoinFieldDestination":"parent",
                                                                    "joiningConstraint":false,
                                                                    "iHRISField":[
                                                                        
                                                                        {
                                                                            "fieldId":"dependents",
                                                                            "iHRISFieldAlias":"dependents",
                                                                            "fhirField":"dependents",
                                                                            "active":false,
                                                                            "fhirBaseElement":"Practitioner",
                                                                            "extension":{
                                                                                "extensionName":"iHRISPractitionerDependents",
                                                                                "fieldType":"integer"
                                                                            }
                                                                        },
                                                                        {
                                                                            "fieldId":"birth_date",
                                                                            "iHRISFieldAlias":"birthdate",
                                                                            "fhirField":"birthDate",
                                                                            "active":false,
                                                                            "fhirBaseElement":"Practitioner"
                                                                        }
                                                                    ],
                                                                    "extension":[{
                                                                        "extensionName":"iHRISPractitionerIdentityDetails",
                                                                        "fhirBaseElement":"Practitioner",
                                                                        "type":"inGroup",
                                                                        "appliedFields":"",
                                                                        "iHRISField":[
                                                                            {
                                                                                "fieldId":"name_father",
                                                                                "iHRISFieldAlias":"name_father",
                                                                                "fhirField":"fatherNames",
                                                                                "active":false,
                                                                                "fieldType":"string"
                                                                            },
                                                                            {
                                                                                "fieldId":"name_mother",
                                                                                "iHRISFieldAlias":"name_mother",
                                                                                "fhirField":"motherNames",
                                                                                "active":false,
                                                                                "fieldType":"string"
                                                                            }
                                                                        ]
                                                                    }],
                                                                    "iHRISJoinedForms":[
                                                                        {
                                                                            "iHRISForm":"gender",
                                                                            "iHRISFormAlias":"gender",
                                                                            "iHRISFormJoinFieldSource":"gender",
                                                                            "iHRISFormJoinFieldDestination":"id",
                                                                            "joiningConstraint":false,
                                                                            "iHRISField":[
                                                                                {
                                                                                    "fieldId":"name",
                                                                                    "iHRISFieldAlias":"gender",
                                                                                    "fhirField":"gender",
                                                                                    "active":true,
                                                                                    "fhirBaseElement":"Practitioner"
                                                                                }
                                                                            ]
                                                                        },
                                                                        {
                                                                            "iHRISForm":"marital_status",
                                                                            "iHRISFormAlias":"marital_status",
                                                                            "iHRISFormJoinFieldSource":"marital_status",
                                                                            "iHRISFormJoinFieldDestination":"id",
                                                                            "joiningConstraint":false,
                                                                            "iHRISField":[
                                                                                {
                                                                                    "fieldId":"name",
                                                                                    "iHRISFieldAlias":"marital_status",
                                                                                    "fhirField":"maritalStatus",
                                                                                    "active":false,
                                                                                    "fhirBaseElement":"Practitioner",
                                                                                    "extension":{
                                                                                        "extensionName":"iHRISPractitionerMaritalStatus",
                                                                                        "fieldType":"code"
                                                                                    }
                                                                                }
                                                                            ]
                                                                        }
                                                                    ]
                                                
                                                                },
                                                                {
                                                                    "iHRISForm":"person_contact_personal",
                                                                    "iHRISFormAlias":"person_contact_personal",
                                                                    "iHRISFormJoinFieldSource":"id",
                                                                    "iHRISFormJoinFieldDestination":"parent",
                                                                    "joiningConstraint":true,
                                                                    "iHRISField":[
                                                
                                                                        {
                                                                            "fieldId":"telephone",
                                                                            "iHRISFieldAlias":"home_phone",
                                                                            "fhirField":"value",
                                                                            "active":false,
                                                                            "fhirBaseElement":"telecom"
                                                                        },
                                                                        {
                                                                            "fieldId":"mobile_phone",
                                                                            "iHRISFieldAlias":"home_phone",
                                                                            "fhirField":"value",
                                                                            "active":true,
                                                                            "fhirBaseElement":"telecom"
                                                                        },
                                                                        {
                                                                            "fieldId":"alt_telephone",
                                                                            "iHRISFieldAlias":"home_autres",
                                                                            "fhirField":"value",
                                                                            "active":false,
                                                                            "fhirBaseElement":"telecom"
                                                                        },
                                                                        {
                                                                            "fieldId":"email",
                                                                            "iHRISFieldAlias":"home_email",
                                                                            "fhirField":"value",
                                                                            "active":true,
                                                                            "fhirBaseElement":"telecom"
                                                                        },
                                                                        {
                                                                            "fieldId":"address",
                                                                            "iHRISFieldAlias":"home_address",
                                                                            "fhirField":"text",
                                                                            "active":true,
                                                                            "fhirBaseElement":"address"
                                                                        }
                                                                    ]
                                                                },
                                                                {
                                                                    "iHRISForm":"person_contact_work",
                                                                    "iHRISFormAlias":"person_contact_work",
                                                                    "iHRISFormJoinFieldSource":"id",
                                                                    "iHRISFormJoinFieldDestination":"parent",
                                                                    "joiningConstraint":false,
                                                                    "iHRISField":[
                                                
                                                                        {
                                                                            "fieldId":"telephone",
                                                                            "iHRISFieldAlias":"work_phone",
                                                                            "fhirField":"value",
                                                                            "active":false,
                                                                            "fhirBaseElement":"telecom"
                                                                        },
                                                                        {
                                                                            "fieldId":"mobile_phone",
                                                                            "iHRISFieldAlias":"work_mobile",
                                                                            "fhirField":"value",
                                                                            "active":false,
                                                                            "fhirBaseElement":"telecom"
                                                                        },
                                                                        {
                                                                            "fieldId":"email",
                                                                            "iHRISFieldAlias":"work_email",
                                                                            "fhirField":"value",
                                                                            "active":false,
                                                                            "fhirBaseElement":"telecom"
                                                                        },
                                                                        {
                                                                            "fieldId":"address",
                                                                            "iHRISFieldAlias":"work_address",
                                                                            "fhirField":"text",
                                                                            "active":false,
                                                                            "fhirBaseElement":"address"
                                                                        }
                                                                    ]
                                                                }
                                                            ]
                                        
                                                        }]
                                
                                                }
                                            ]
                                
                                        }
                                    ]
                        
                                }
                            ]
                
                        }]
        
                }]

        }],
    "fieldsLinked":[
        {
            "iHRISForm":"person_id",
            "iHRISField":[
                {
                    "fieldId":"id_num",
                    "iHRISFieldAlias":"id_num",
                    "fhirField":"value",
                    "active":true,
                    "fhirBaseElement":"identifier"
                },
                {
                    "fieldId":"expiration_date",
                    "iHRISFieldAlias":"id_expiration_date",
                    "fhirField":"period.end",
                    "active":false,
                    "fhirBaseElement":"identifier"
                }
            ],
            "iHRISJoinedForms":[
                {
                    "iHRISForm":"id_type",
                    "iHRISFormAlias":"id_type",
                    "iHRISFormJoinFieldSource":"id_type",
                    "iHRISFormJoinFieldDestination":"id",
                    "joiningConstraint":true,
                    "iHRISField":[
                        {
                            "fieldId":"name",
                            "iHRISFieldAlias":"type_name",
                            "fhirField":"type_display",
                            "active":true,
                            "fhirBaseElement":"identifier"
                        },
                        {
                            "fieldId":"id",
                            "iHRISFieldAlias":"id_type",
                            "fhirField":"type_code",
                            "active":true,
                            "fhirBaseElement":"identifier"
                        }

                    ]
                }
                
            ]
        }
    ],
    "configs":{
        "identifierSystemUrl":"http://ihris.org/fhir/CodeSystem/ihris-rdc",
        "profile":"http://ihris.org/fhir/StructureDefinition/ihris-practitioner",
        "extensionUrl":"http://ihris.org/fhir/StructureDefinition/",
        "nameUse":"official",
        "binaryServerUrl":"http://localhost/ihris_photo/",
        "docServerUrl":"http://localhost/ihris_docs/",
        "photoFileExtension":".jpg",
        "transformQualificationInstitutionNameToId":{
            "iHRISFieldAlias":"education_institution,dip_training_institution,registration_board"
        },
        "concatenateDocServerUrl":{
            "iHRISFieldAlias":"doc_url",
            "value":"http://localhost/ihris_docs/"
        },
        "appendCountryCodeToPhoneNumber":{
            "value":"+243"
        },
        "removeiHRISPrefixForCodeableConcept":true,
        "genderCode":{
            "Male":"male",
            "Female":"female",
            "autres":"other"
        },
        "defaultIdentifierCodeableConcept":{
            "code":"IHRSID",
            "display":"Internal IHRIS ID"
        },
        "limitLocationForm":{
            "status":true,
            "form":"region",
            "fieldName":"id",
            "value":"region|KN"
        }
    }
}